{
  "timestamp": "2025-08-15T16:40:28.533380",
  "data": {
    "stock_code": "3443",
    "stock_name": "創意",
    "current_price": 1205.0,
    "analysis_time": "2025-08-15T16:40:28.533380",
    "price_change_1d": 0.0,
    "price_change_5d": -2.03,
    "price_change_20d": 0,
    "rsi": 41.18,
    "macd": 3.433,
    "signal": 0,
    "histogram": 3.433,
    "ma5": 1192.0,
    "ma10": 1228.5,
    "ma20": 1228.5,
    "ma60": 1228.5,
    "bb_upper": 1311.93,
    "bb_middle": 1228.5,
    "bb_lower": 1145.07,
    "volume": 1017,
    "signals": [
      [
        "RSI中性",
        "持有觀望",
        "gray"
      ]
    ],
    "score": 70
  }
}